optionxray/__init__.py
optionxray/bs.py
optionxray/greeks.py
optionxray/instruments.py
optionxray/iv.py
optionxray/report.py
optionxray/scenarios.py
optionxray/xray.py
optionxray-0.1.0.dist-info/licenses/LICENSE
optionxray-0.1.0.dist-info/METADATA
optionxray-0.1.0.dist-info/WHEEL
optionxray-0.1.0.dist-info/top_level.txt
optionxray-0.1.0.dist-info/RECORD
