Metadata-Version: 2.4
Name: optionxray
Version: 0.1.0
Summary: Option pricing and explanation engine with Black-Scholes analytics
Author: OptionXRay Contributors
License: MIT License
Project-URL: Homepage, https://github.com/optionxray/optionxray
Project-URL: Repository, https://github.com/optionxray/optionxray
Project-URL: Issues, https://github.com/optionxray/optionxray/issues
Keywords: options,derivatives,black-scholes,greeks,finance
Classifier: Development Status :: 3 - Alpha
Classifier: Intended Audience :: Financial and Insurance Industry
Classifier: License :: OSI Approved :: MIT License
Classifier: Programming Language :: Python :: 3
Classifier: Programming Language :: Python :: 3 :: Only
Classifier: Programming Language :: Python :: 3.9
Classifier: Programming Language :: Python :: 3.10
Classifier: Programming Language :: Python :: 3.11
Classifier: Programming Language :: Python :: 3.12
Classifier: Topic :: Office/Business :: Financial
Classifier: Topic :: Scientific/Engineering :: Mathematics
Requires-Python: >=3.9
License-File: LICENSE
Requires-Dist: numpy>=1.22
Requires-Dist: pandas>=1.5
Requires-Dist: scipy>=1.9
Provides-Extra: test
Requires-Dist: pytest>=7.0; extra == "test"
Dynamic: license-file
